pydynox/__init__.py
pydynox/_internal/__init__.py
pydynox/_internal/_atomic.py
pydynox/_internal/_compression.py
pydynox/_internal/_conditions.py
pydynox/_internal/_encryption.py
pydynox/_internal/_indexes.py
pydynox/_internal/_logging.py
pydynox/_internal/_metrics.py
pydynox/_internal/_model/__init__.py
pydynox/_internal/_model/_async.py
pydynox/_internal/_model/_base.py
pydynox/_internal/_model/_batch.py
pydynox/_internal/_model/_crud.py
pydynox/_internal/_model/_helpers.py
pydynox/_internal/_model/_query.py
pydynox/_internal/_model/_s3_helpers.py
pydynox/_internal/_model/_ttl.py
pydynox/_internal/_model/_version.py
pydynox/_internal/_operations_metrics.py
pydynox/_internal/_results.py
pydynox/_internal/_s3.py
pydynox/_internal/_tracing.py
pydynox/atomic.py
pydynox/attributes/__init__.py
pydynox/attributes/base.py
pydynox/attributes/compressed.py
pydynox/attributes/encrypted.py
pydynox/attributes/primitives.py
pydynox/attributes/s3.py
pydynox/attributes/sets.py
pydynox/attributes/special.py
pydynox/attributes/ttl.py
pydynox/attributes/version.py
pydynox/batch_operations.py
pydynox/client/__init__.py
pydynox/client/_base.py
pydynox/client/_batch.py
pydynox/client/_client.py
pydynox/client/_crud.py
pydynox/client/_partiql.py
pydynox/client/_query.py
pydynox/client/_scan.py
pydynox/client/_table.py
pydynox/conditions.py
pydynox/config.py
pydynox/diagnostics/__init__.py
pydynox/diagnostics/hot_partition.py
pydynox/exceptions.py
pydynox/generators.py
pydynox/hooks.py
pydynox/indexes.py
pydynox/integrations/__init__.py
pydynox/integrations/_base.py
pydynox/integrations/dataclass.py
pydynox/integrations/functions.py
pydynox/integrations/opentelemetry.py
pydynox/integrations/pydantic.py
pydynox/model.py
pydynox/py.typed
pydynox/pydynox_core.cpython-312-x86_64-linux-gnu.so
pydynox/pydynox_core.pyi
pydynox/query.py
pydynox/rate_limit.py
pydynox/size.py
pydynox/testing/__init__.py
pydynox/testing/memory.py
pydynox/testing/pytest_plugin.py
pydynox/transaction.py
pydynox-0.24.0.dist-info/METADATA
pydynox-0.24.0.dist-info/WHEEL
pydynox-0.24.0.dist-info/entry_points.txt
pydynox-0.24.0.dist-info/licenses/LICENSE
pydynox-0.24.0.dist-info/RECORD
