Metadata-Version: 2.4
Name: pydynox
Version: 0.24.0
Classifier: Development Status :: 3 - Alpha
Classifier: Intended Audience :: Developers
Classifier: License :: OSI Approved :: Apache Software License
Classifier: Programming Language :: Python :: 3
Classifier: Programming Language :: Python :: 3.11
Classifier: Programming Language :: Python :: 3.12
Classifier: Programming Language :: Python :: 3.13
Classifier: Programming Language :: Python :: 3.14
Classifier: Programming Language :: Rust
Classifier: Topic :: Database
Requires-Dist: opentelemetry-api>=1.0 ; extra == 'opentelemetry'
Requires-Dist: pydantic>=2.0 ; extra == 'pydantic'
Provides-Extra: opentelemetry
Provides-Extra: pydantic
License-File: LICENSE
Summary: A fast DynamoDB ORM for Python with a Rust core
Keywords: dynamodb,orm,aws,rust,python
Home-Page: https://github.com/ferrumio/pydynox
Author-email: Leandro Cavalcante Damascena <leandro.damascena@gmail.com>
License: Apache-2.0
Requires-Python: >=3.11
Project-URL: Documentation, https://ferrumio.github.io/pydynox
Project-URL: Homepage, https://github.com/ferrumio/pydynox
Project-URL: Repository, https://github.com/ferrumio/pydynox
